datasette_reconcile/__about__.py
datasette_reconcile/__init__.py
datasette_reconcile/reconcile.py
datasette_reconcile/settings.py
datasette_reconcile/utils.py
datasette_reconcile-0.6.3.dist-info/METADATA
datasette_reconcile-0.6.3.dist-info/WHEEL
datasette_reconcile-0.6.3.dist-info/entry_points.txt
datasette_reconcile-0.6.3.dist-info/licenses/LICENSE.txt
datasette_reconcile-0.6.3.dist-info/RECORD
