Metadata-Version: 2.1
Name: datasette-reconcile
Version: 0.6.3
Summary: Adds a reconciliation API to Datasette.
Project-URL: Documentation, https://github.com/drkane/datasette-reconcile#readme
Project-URL: Issues, https://github.com/drkane/datasette-reconcile/issues
Project-URL: Source, https://github.com/drkane/datasette-reconcile
Project-URL: CI, https://github.com/drkane/datasette-reconcile/actions
Project-URL: Changelog, https://github.com/drkane/datasette-reconcile/releases
Author-email: David Kane <david@dkane.net>
License-Expression: MIT
License-File: LICENSE.txt
Classifier: Development Status :: 4 - Beta
Classifier: Framework :: Datasette
Classifier: Programming Language :: Python
Classifier: Programming Language :: Python :: 3.8
Classifier: Programming Language :: Python :: 3.9
Classifier: Programming Language :: Python :: 3.10
Classifier: Programming Language :: Python :: 3.11
Classifier: Programming Language :: Python :: 3.12
Classifier: Programming Language :: Python :: Implementation :: CPython
Classifier: Programming Language :: Python :: Implementation :: PyPy
Requires-Python: >=3.7
Requires-Dist: datasette
Requires-Dist: fuzzywuzzy[speedup]
Provides-Extra: lint
Requires-Dist: mypy>=1.0.0; extra == 'lint'
Requires-Dist: ruff>=0.1.8; extra == 'lint'
Provides-Extra: test
Requires-Dist: coverage[toml]>=6.5; extra == 'test'
Requires-Dist: httpx; extra == 'test'
Requires-Dist: jsonschema; extra == 'test'
Requires-Dist: pytest; extra == 'test'
Requires-Dist: pytest-asyncio; extra == 'test'
Requires-Dist: sqlite-utils; extra == 'test'
